item_based_recommender/__init__.py
item_based_recommender/_nbdev.py
item_based_recommender/core.py
item_based_recommender/model.py
item_based_recommender-1.0.0.dist-info/LICENSE
item_based_recommender-1.0.0.dist-info/METADATA
item_based_recommender-1.0.0.dist-info/WHEEL
item_based_recommender-1.0.0.dist-info/entry_points.txt
item_based_recommender-1.0.0.dist-info/top_level.txt
item_based_recommender-1.0.0.dist-info/RECORD
